{"_path":"/","_dir":"","_draft":false,"_partial":false,"_locale":"","title":"Home","description":"100세까지 건강하게 개발하기 프로젝트.","layout":"default","head":{"title":"Techy100.com"},"body":{"type":"root","children":[{"type":"element","tag":"hero","props":{"image":"/social-card-preview.jpg"},"children":[{"type":"element","tag":"template","props":{"v-slot:title":""},"children":[{"type":"element","tag":"p","props":{},"children":[{"type":"text","value":"100세까지 건강하게 개발하기 프로젝트 진행 중..."}]}]},{"type":"element","tag":"template","props":{"v-slot:description":""},"children":[{"type":"element","tag":"ul","props":{},"children":[{"type":"element","tag":"li","props":{},"children":[{"type":"text","value":"100세까지 건강한 신체와 정신으로 새로운 기술을 배우며 개발 하자!"}]},{"type":"element","tag":"li","props":{},"children":[{"type":"text","value":"gw-basic을 시작으로 90년대에 리눅스에서 c/c++로 개발. cgi, php로 웹페이지 제작."}]},{"type":"element","tag":"li","props":{},"children":[{"type":"text","value":"2010년대에 java, jsp, js로 웹페이지 개발, 안드로이드도 같이 개발."}]},{"type":"element","tag":"li","props":{},"children":[{"type":"text","value":"2020년대에 node, vue에 입문."}]},{"type":"element","tag":"li","props":{},"children":[{"type":"text","value":"이제는 AI를 배워야 하나?"}]}]}]}]},{"type":"element","tag":"ul","props":{},"children":[{"type":"element","tag":"li","props":{},"children":[{"type":"text","value":"홈페이지는 markdown 파일로 html 파일을 생성하기 위해서 "},{"type":"element","tag":"a","props":{"href":"https://nuxt.com","rel":["nofollow"]},"children":[{"type":"text","value":"nuxt"}]},{"type":"text","value":"를 이용합니다."}]},{"type":"element","tag":"li","props":{},"children":[{"type":"text","value":"markdown 문법은 "},{"type":"element","tag":"a","props":{"href":"https://www.markdownguide.org/basic-syntax","rel":["nofollow"]},"children":[{"type":"text","value":"https://www.markdownguide.org/basic-syntax"}]},{"type":"text","value":" 사이트를 참고합니다."}]}]},{"type":"element","tag":"gallery","props":{":images":"[\"/img/techy100/my_2024.jpg\",\"/img/techy100/my_90s_com.jpg\"]"},"children":[]},{"type":"element","tag":"h3","props":{"id":"alpine-템플릿-참고-사항"},"children":[{"type":"text","value":"Alpine 템플릿 참고 사항"}]},{"type":"element","tag":"p","props":{},"children":[{"type":"element","tag":"a","props":{"href":"https://nuxt.com","rel":["nofollow"]},"children":[{"type":"text","value":"nuxt"}]},{"type":"text","value":"를 이용 시에 블로그용 템플릿으로 "},{"type":"element","tag":"a","props":{"href":"https://github.com/nuxt-themes/alpine","rel":["nofollow"]},"children":[{"type":"text","value":"alpine"}]},{"type":"text","value":"을 사용합니다."}]},{"type":"element","tag":"pre","props":{"className":"language-sh shiki shiki-themes github-light github-dark","code":"npx nuxi@latest init techy100-nuxt-alpine -t themes/alpine\n","language":"sh","meta":"","style":""},"children":[{"type":"element","tag":"code","props":{"__ignoreMap":""},"children":[{"type":"element","tag":"span","props":{"class":"line","line":1},"children":[{"type":"element","tag":"span","props":{"style":"--shiki-default:#6F42C1;--shiki-dark:#B392F0"},"children":[{"type":"text","value":"npx"}]},{"type":"element","tag":"span","props":{"style":"--shiki-default:#032F62;--shiki-dark:#9ECBFF"},"children":[{"type":"text","value":" nuxi@latest"}]},{"type":"element","tag":"span","props":{"style":"--shiki-default:#032F62;--shiki-dark:#9ECBFF"},"children":[{"type":"text","value":" init"}]},{"type":"element","tag":"span","props":{"style":"--shiki-default:#032F62;--shiki-dark:#9ECBFF"},"children":[{"type":"text","value":" techy100-nuxt-alpine"}]},{"type":"element","tag":"span","props":{"style":"--shiki-default:#005CC5;--shiki-dark:#79B8FF"},"children":[{"type":"text","value":" -t"}]},{"type":"element","tag":"span","props":{"style":"--shiki-default:#032F62;--shiki-dark:#9ECBFF"},"children":[{"type":"text","value":" themes/alpine\n"}]}]}]}]},{"type":"element","tag":"blockquote","props":{},"children":[{"type":"element","tag":"ul","props":{},"children":[{"type":"element","tag":"li","props":{},"children":[{"type":"text","value":"markdown 파일에서 소스코드 하이라이트는 "},{"type":"element","tag":"a","props":{"href":"https://github.com/antfu/shikiji","rel":["nofollow"]},"children":[{"type":"text","value":"shikiji"}]},{"type":"text","value":"가 사용되고, 지원되는 언어는 "},{"type":"element","tag":"a","props":{"href":"https://shikiji.netlify.app/languages","rel":["nofollow"]},"children":[{"type":"text","value":"지원언어목록"}]},{"type":"text","value":"에서 확인 가능합니다."}]},{"type":"element","tag":"li","props":{},"children":[{"type":"element","tag":"a","props":{"href":"https://analytics.google.com/","rel":["nofollow"]},"children":[{"type":"text","value":"google analytics"}]},{"type":"text","value":" 지원을 위해서 "},{"type":"element","tag":"a","props":{"href":"https://nuxt.com/modules/gtag","rel":["nofollow"]},"children":[{"type":"text","value":"gtag nuxt 모듈"}]},{"type":"text","value":"을 사용합니다."}]},{"type":"element","tag":"li","props":{},"children":[{"type":"element","tag":"a","props":{"href":"https://github.com/nuxt-themes/alpine","rel":["nofollow"]},"children":[{"type":"text","value":"open source blog theme"}]},{"type":"text","value":" powered by "},{"type":"element","tag":"a","props":{"href":"https://content.nuxtjs.org","rel":["nofollow"]},"children":[{"type":"text","value":"Nuxt Content"}]},{"type":"text","value":", editable on "},{"type":"element","tag":"a","props":{"href":"https://nuxt.studio","rel":["nofollow"]},"children":[{"type":"text","value":"Nuxt Studio"}]},{"type":"text","value":"."}]},{"type":"element","tag":"li","props":{},"children":[{"type":"text","value":"Write pages in Markdown and Vue components with the "},{"type":"element","tag":"a","props":{"href":"https://content.nuxtjs.org/guide/writing/mdc","rel":["nofollow"]},"children":[{"type":"text","value":"MDC syntax"}]},{"type":"text","value":"."}]},{"type":"element","tag":"li","props":{},"children":[{"type":"text","value":"Use "},{"type":"element","tag":"a","props":{"href":"https://elements.nuxt.space","rel":["nofollow"]},"children":[{"type":"element","tag":"strong","props":{},"children":[{"type":"text","value":"30+ built-in"}]}]},{"type":"text","value":" components in your Markdown pages."}]}]}]},{"type":"element","tag":"gallery","props":{":images":"[\"/img/alpine/get-started.webp\",\"/img/alpine/configure-alpine.webp\",\"/img/alpine/write-articles.webp\",\"/img/alpine/design-tokens.webp\"]"},"children":[]},{"type":"element","tag":"style","props":{},"children":[{"type":"text","value":"html.dark .shiki span {color: var(--shiki-dark);background: var(--shiki-dark-bg);font-style: var(--shiki-dark-font-style);font-weight: var(--shiki-dark-font-weight);text-decoration: var(--shiki-dark-text-decoration);}html .shiki span {color: var(--shiki-default);background: var(--shiki-default-bg);font-style: var(--shiki-default-font-style);font-weight: var(--shiki-default-font-weight);text-decoration: var(--shiki-default-text-decoration);}html .default .shiki span {color: var(--shiki-default);background: var(--shiki-default-bg);font-style: var(--shiki-default-font-style);font-weight: var(--shiki-default-font-weight);text-decoration: var(--shiki-default-text-decoration);}html .dark .shiki span {color: var(--shiki-dark);background: var(--shiki-dark-bg);font-style: var(--shiki-dark-font-style);font-weight: var(--shiki-dark-font-weight);text-decoration: var(--shiki-dark-text-decoration);}"}]}],"toc":{"title":"","searchDepth":2,"depth":2,"links":[{"id":"alpine-템플릿-참고-사항","depth":3,"text":"Alpine 템플릿 참고 사항"}]}},"_type":"markdown","_id":"content:1.index.md","_source":"content","_file":"1.index.md","_extension":"md"}