{"_path":"/server/ubuntu-init","_dir":"server","_draft":false,"_partial":false,"_locale":"","title":"Ubuntu 설치 후 패키지 업그레이드, 타임존 설정","description":"Ubuntu 22.04 설치 후 패키지 업그레이드, 타임존 설정","cover":"/img/server/ubuntu-0002-01.jpg","date":"2022-04-30T00:00:00.000Z","layout":"article","body":{"type":"root","children":[{"type":"element","tag":"h1","props":{"id":"ubuntu-설치-후-패키지-업그레이드-타임존-설정"},"children":[{"type":"text","value":"Ubuntu 설치 후 패키지 업그레이드, 타임존 설정"}]},{"type":"element","tag":"p","props":{},"children":[{"type":"text","value":"ubuntu 22.04 서버 설치 후 기본 설정한 것들 입니다.\n패키지를 최신으로 업그레이드 하고 타임존을 "},{"type":"element","tag":"code","props":{"className":[]},"children":[{"type":"text","value":"Asia/Seoul"}]},{"type":"text","value":"로 변경합니다."}]},{"type":"element","tag":"h2","props":{"id":"시스템-업데이트"},"children":[{"type":"text","value":"시스템 업데이트"}]},{"type":"element","tag":"p","props":{},"children":[{"type":"text","value":"신규 패키지 설치전에는 먼저 시스템을 최신으로 업데이트하고 시작합니다."}]},{"type":"element","tag":"pre","props":{"className":"language-bash shiki shiki-themes github-light github-dark","code":"sudo apt update\nsudo apt -y upgrade\n","language":"bash","meta":"","style":""},"children":[{"type":"element","tag":"code","props":{"__ignoreMap":""},"children":[{"type":"element","tag":"span","props":{"class":"line","line":1},"children":[{"type":"element","tag":"span","props":{"style":"--shiki-default:#6F42C1;--shiki-dark:#B392F0"},"children":[{"type":"text","value":"sudo"}]},{"type":"element","tag":"span","props":{"style":"--shiki-default:#032F62;--shiki-dark:#9ECBFF"},"children":[{"type":"text","value":" apt"}]},{"type":"element","tag":"span","props":{"style":"--shiki-default:#032F62;--shiki-dark:#9ECBFF"},"children":[{"type":"text","value":" update\n"}]}]},{"type":"element","tag":"span","props":{"class":"line","line":2},"children":[{"type":"element","tag":"span","props":{"style":"--shiki-default:#6F42C1;--shiki-dark:#B392F0"},"children":[{"type":"text","value":"sudo"}]},{"type":"element","tag":"span","props":{"style":"--shiki-default:#032F62;--shiki-dark:#9ECBFF"},"children":[{"type":"text","value":" apt"}]},{"type":"element","tag":"span","props":{"style":"--shiki-default:#005CC5;--shiki-dark:#79B8FF"},"children":[{"type":"text","value":" -y"}]},{"type":"element","tag":"span","props":{"style":"--shiki-default:#032F62;--shiki-dark:#9ECBFF"},"children":[{"type":"text","value":" upgrade\n"}]}]}]}]},{"type":"element","tag":"h2","props":{"id":"timezone-설정"},"children":[{"type":"text","value":"timezone 설정"}]},{"type":"element","tag":"p","props":{},"children":[{"type":"element","tag":"code","props":{"className":[]},"children":[{"type":"text","value":"date"}]},{"type":"text","value":" 명령으로 시간을 확인해보면 "},{"type":"element","tag":"code","props":{"className":[]},"children":[{"type":"text","value":"UTC"}]},{"type":"text","value":"로 타임존이 설정되어 있습니다.\n"},{"type":"element","tag":"code","props":{"className":[]},"children":[{"type":"text","value":"timedatectl"}]},{"type":"text","value":" 명령으로 "},{"type":"element","tag":"code","props":{"className":[]},"children":[{"type":"text","value":"Asia/Seoul"}]},{"type":"text","value":"로 변경합니다."}]},{"type":"element","tag":"pre","props":{"className":"language-bash shiki shiki-themes github-light github-dark","code":"appaga@appagakr:~$ date\nSat Apr 30 01:04:52 PM UTC 2022\nappaga@appagakr:~$ sudo timedatectl set-timezone Asia/Seoul\n[sudo] password for appaga:\nappaga@appagakr:~$ date\nSat Apr 30 10:06:01 PM KST 2022\n","language":"bash","meta":"","style":""},"children":[{"type":"element","tag":"code","props":{"__ignoreMap":""},"children":[{"type":"element","tag":"span","props":{"class":"line","line":1},"children":[{"type":"element","tag":"span","props":{"style":"--shiki-default:#6F42C1;--shiki-dark:#B392F0"},"children":[{"type":"text","value":"appaga@appagakr:~$"}]},{"type":"element","tag":"span","props":{"style":"--shiki-default:#032F62;--shiki-dark:#9ECBFF"},"children":[{"type":"text","value":" date\n"}]}]},{"type":"element","tag":"span","props":{"class":"line","line":2},"children":[{"type":"element","tag":"span","props":{"style":"--shiki-default:#6F42C1;--shiki-dark:#B392F0"},"children":[{"type":"text","value":"Sat"}]},{"type":"element","tag":"span","props":{"style":"--shiki-default:#032F62;--shiki-dark:#9ECBFF"},"children":[{"type":"text","value":" Apr"}]},{"type":"element","tag":"span","props":{"style":"--shiki-default:#005CC5;--shiki-dark:#79B8FF"},"children":[{"type":"text","value":" 30"}]},{"type":"element","tag":"span","props":{"style":"--shiki-default:#005CC5;--shiki-dark:#79B8FF"},"children":[{"type":"text","value":" 01"}]},{"type":"element","tag":"span","props":{"style":"--shiki-default:#032F62;--shiki-dark:#9ECBFF"},"children":[{"type":"text","value":":04:52"}]},{"type":"element","tag":"span","props":{"style":"--shiki-default:#032F62;--shiki-dark:#9ECBFF"},"children":[{"type":"text","value":" PM"}]},{"type":"element","tag":"span","props":{"style":"--shiki-default:#032F62;--shiki-dark:#9ECBFF"},"children":[{"type":"text","value":" UTC"}]},{"type":"element","tag":"span","props":{"style":"--shiki-default:#005CC5;--shiki-dark:#79B8FF"},"children":[{"type":"text","value":" 2022\n"}]}]},{"type":"element","tag":"span","props":{"class":"line","line":3},"children":[{"type":"element","tag":"span","props":{"style":"--shiki-default:#6F42C1;--shiki-dark:#B392F0"},"children":[{"type":"text","value":"appaga@appagakr:~$"}]},{"type":"element","tag":"span","props":{"style":"--shiki-default:#032F62;--shiki-dark:#9ECBFF"},"children":[{"type":"text","value":" sudo"}]},{"type":"element","tag":"span","props":{"style":"--shiki-default:#032F62;--shiki-dark:#9ECBFF"},"children":[{"type":"text","value":" timedatectl"}]},{"type":"element","tag":"span","props":{"style":"--shiki-default:#032F62;--shiki-dark:#9ECBFF"},"children":[{"type":"text","value":" set-timezone"}]},{"type":"element","tag":"span","props":{"style":"--shiki-default:#032F62;--shiki-dark:#9ECBFF"},"children":[{"type":"text","value":" Asia/Seoul\n"}]}]},{"type":"element","tag":"span","props":{"class":"line","line":4},"children":[{"type":"element","tag":"span","props":{"style":"--shiki-default:#24292E;--shiki-dark:#E1E4E8"},"children":[{"type":"text","value":"[sudo] password "}]},{"type":"element","tag":"span","props":{"style":"--shiki-default:#D73A49;--shiki-dark:#F97583"},"children":[{"type":"text","value":"for"}]},{"type":"element","tag":"span","props":{"style":"--shiki-default:#24292E;--shiki-dark:#E1E4E8"},"children":[{"type":"text","value":" appaga:\n"}]}]},{"type":"element","tag":"span","props":{"class":"line","line":5},"children":[{"type":"element","tag":"span","props":{"style":"--shiki-default:#6F42C1;--shiki-dark:#B392F0"},"children":[{"type":"text","value":"appaga@appagakr:~$"}]},{"type":"element","tag":"span","props":{"style":"--shiki-default:#032F62;--shiki-dark:#9ECBFF"},"children":[{"type":"text","value":" date\n"}]}]},{"type":"element","tag":"span","props":{"class":"line","line":6},"children":[{"type":"element","tag":"span","props":{"style":"--shiki-default:#6F42C1;--shiki-dark:#B392F0"},"children":[{"type":"text","value":"Sat"}]},{"type":"element","tag":"span","props":{"style":"--shiki-default:#032F62;--shiki-dark:#9ECBFF"},"children":[{"type":"text","value":" Apr"}]},{"type":"element","tag":"span","props":{"style":"--shiki-default:#005CC5;--shiki-dark:#79B8FF"},"children":[{"type":"text","value":" 30"}]},{"type":"element","tag":"span","props":{"style":"--shiki-default:#005CC5;--shiki-dark:#79B8FF"},"children":[{"type":"text","value":" 10"}]},{"type":"element","tag":"span","props":{"style":"--shiki-default:#032F62;--shiki-dark:#9ECBFF"},"children":[{"type":"text","value":":06:01"}]},{"type":"element","tag":"span","props":{"style":"--shiki-default:#032F62;--shiki-dark:#9ECBFF"},"children":[{"type":"text","value":" PM"}]},{"type":"element","tag":"span","props":{"style":"--shiki-default:#032F62;--shiki-dark:#9ECBFF"},"children":[{"type":"text","value":" KST"}]},{"type":"element","tag":"span","props":{"style":"--shiki-default:#005CC5;--shiki-dark:#79B8FF"},"children":[{"type":"text","value":" 2022\n"}]}]}]}]},{"type":"element","tag":"style","props":{},"children":[{"type":"text","value":"html.dark .shiki span {color: var(--shiki-dark);background: var(--shiki-dark-bg);font-style: var(--shiki-dark-font-style);font-weight: var(--shiki-dark-font-weight);text-decoration: var(--shiki-dark-text-decoration);}html .shiki span {color: var(--shiki-default);background: var(--shiki-default-bg);font-style: var(--shiki-default-font-style);font-weight: var(--shiki-default-font-weight);text-decoration: var(--shiki-default-text-decoration);}html .default .shiki span {color: var(--shiki-default);background: var(--shiki-default-bg);font-style: var(--shiki-default-font-style);font-weight: var(--shiki-default-font-weight);text-decoration: var(--shiki-default-text-decoration);}html .dark .shiki span {color: var(--shiki-dark);background: var(--shiki-dark-bg);font-style: var(--shiki-dark-font-style);font-weight: var(--shiki-dark-font-weight);text-decoration: var(--shiki-dark-text-decoration);}"}]}],"toc":{"title":"","searchDepth":2,"depth":2,"links":[{"id":"시스템-업데이트","depth":2,"text":"시스템 업데이트"},{"id":"timezone-설정","depth":2,"text":"timezone 설정"}]}},"_type":"markdown","_id":"content:server:0002.ubuntu-init.md","_source":"content","_file":"server/0002.ubuntu-init.md","_extension":"md"}